selfish/__init__.py
selfish/__main__.py
selfish/_version.py
selfish/selfish.py
selfish_hic-1.14.0.dist-info/LICENSE
selfish_hic-1.14.0.dist-info/METADATA
selfish_hic-1.14.0.dist-info/WHEEL
selfish_hic-1.14.0.dist-info/entry_points.txt
selfish_hic-1.14.0.dist-info/top_level.txt
selfish_hic-1.14.0.dist-info/RECORD
